qg_tool/__init__.py
qg_tool/tool.py
qg_tool-0.0.2.dist-info/METADATA
qg_tool-0.0.2.dist-info/WHEEL
qg_tool-0.0.2.dist-info/top_level.txt
qg_tool-0.0.2.dist-info/RECORD
