Metadata-Version: 2.1
Name: qg-tool
Version: 0.0.2
Summary: 全高工具类
Home-page: http://192.168.117.144/toolkit/qg_tool
Author: zouwendi
Author-email: tz310200@gamil.com
Maintainer: zouwendi
Maintainer-email: tz310200@gamil.com
License: GPL3 License
Platform: all
Classifier: Development Status :: 4 - Beta
Classifier: Operating System :: OS Independent
Classifier: Intended Audience :: Developers
Classifier: Programming Language :: Python
Classifier: Programming Language :: Python :: Implementation
Classifier: Programming Language :: Python :: 3
Classifier: Programming Language :: Python :: 3.4
Classifier: Programming Language :: Python :: 3.5
Classifier: Programming Language :: Python :: 3.5
Classifier: Programming Language :: Python :: 3.6
Classifier: Programming Language :: Python :: 3.7
Classifier: Topic :: Software Development :: Libraries
Requires-Dist: pipreqs (>=0.4.9)
Requires-Dist: setuptools (>=41.0.1)
